setup.cfg
setup.py
asforests/__init__.py
asforests/_exf_classifier.py
asforests/_exf_regressor.py
asforests/_grower.py
asforests/_rf_classifier.py
asforests/_rf_regressor.py
asforests.egg-info/PKG-INFO
asforests.egg-info/SOURCES.txt
asforests.egg-info/dependency_links.txt
asforests.egg-info/requires.txt
asforests.egg-info/top_level.txt